traffic_light_controller.v
module traffic_light_controller (
    input clk,
    input reset,
    input night_mode,
    output reg north,
    output reg east,
    output reg south,
    output reg west,
    output [2:0] debug
);

reg [2:0] state;
reg [2:0] next_state;
reg [3:0] counter;


parameter S0=0, S1=1, S2=2, S3=3, S4=4, S5=5, S6=6, S7=7;

parameter GREEN_TIME = 3;

parameter RED_TIME   = 1;

assign debug = state;


always @(posedge clk or posedge reset) begin
    if (reset)
        state <= S0;
    else if (night_mode)
        state <= S0;
    else if (counter == 0)
        state <= next_state;
end


always @(posedge clk or posedge reset) begin
    if (reset)
        counter <= GREEN_TIME;
    else if (counter == 0) begin
        case(state)
            S0, S2, S4, S6: counter <= RED_TIME;
            default:        counter <= GREEN_TIME;
        endcase
    end
    else
        counter <= counter - 1;
end


always @(*) begin
    case(state)
        S0: next_state = S1;
        S1: next_state = S2;
        S2: next_state = S3;
        S3: next_state = S4;
        S4: next_state = S5;
        S5: next_state = S6;
        S6: next_state = S7;
        S7: next_state = S0;
        default: next_state = S0;
    endcase
end

always @(*) begin
    north = 0;
    east  = 0;
    south = 0;
    west  = 0;

    if (night_mode) begin
        north = counter[0];
        east  = counter[0];
        south = counter[0];
        west  = counter[0];
    end
    else begin
        case(state)
            S0: north = 1;
            S2: east  = 1;
            S4: south = 1;
            S6: west  = 1;
        endcase
    end
end

endmodule

tb_traffic_light.v
`timescale 1ns/1ps
module tb_traffic;

reg clk;
reg reset;
reg night_mode;
wire north, east, south, west;
wire [2:0] debug;

traffic_light_controller uut (
    .clk(clk),
    .reset(reset),
    .night_mode(night_mode),
    .north(north),
    .east(east),
    .south(south),
    .west(west),
    .debug(debug)
);


always #5 clk = ~clk;


initial begin
    $dumpfile("traffic.vcd");
    $dumpvars(0, tb_traffic);
end


initial begin
    clk = 0;
    reset = 1;
    night_mode = 0;

    #10 reset = 0;
    #300;

    
    night_mode = 1;
    #150;

    
    night_mode = 0;
    #300;

    $finish;
end

endmodule

traffic.vcd
$date
	Sat May 02 16:28:45 2026
$end
$version
	Icarus Verilog
$end
$timescale
	1ps
$end
$scope module tb_traffic $end
$var wire 1 ! west $end
$var wire 1 " south $end
$var wire 1 # north $end
$var wire 1 $ east $end
$var wire 3 % debug [2:0] $end
$var reg 1 & clk $end
$var reg 1 ' night_mode $end
$var reg 1 ( reset $end
$scope module uut $end
$var wire 1 & clk $end
$var wire 3 ) debug [2:0] $end
$var wire 1 ' night_mode $end
$var wire 1 ( reset $end
$var parameter 32 * GREEN_TIME $end
$var parameter 32 + RED_TIME $end
$var parameter 32 , S0 $end
$var parameter 32 - S1 $end
$var parameter 32 . S2 $end
$var parameter 32 / S3 $end
$var parameter 32 0 S4 $end
$var parameter 32 1 S5 $end
$var parameter 32 2 S6 $end
$var parameter 32 3 S7 $end
$var reg 4 4 counter [3:0] $end
$var reg 1 $ east $end
$var reg 3 5 next_state [2:0] $end
$var reg 1 # north $end
$var reg 1 " south $end
$var reg 3 6 state [2:0] $end
$var reg 1 ! west $end
$upscope $end
$upscope $end
$enddefinitions $end
$comment Show the parameter values. $end
$dumpall
b111 3
b110 2
b101 1
b100 0
b11 /
b10 .
b1 -
b0 ,
b1 +
b11 *
$end
#0
$dumpvars
b0 6
b1 5
b11 4
b0 )
1(
0'
0&
b0 %
0$
1#
0"
0!
$end
#5000
1&
#10000
0&
0(
#15000
1#
b10 4
1&
#20000
0&
#25000
1#
b1 4
1&
#30000
0&
#35000
1#
b0 4
1&
#40000
0&
#45000
0#
b10 5
b1 4
b1 %
b1 )
b1 6
1&
#50000
0&
#55000
b0 4
1&
#60000
0&
#65000
1$
b11 5
b11 4
b10 %
b10 )
b10 6
1&
#70000
0&
#75000
1$
b10 4
1&
#80000
0&
#85000
1$
b1 4
1&
#90000
0&
#95000
1$
b0 4
1&
#100000
0&
#105000
0$
b100 5
b1 4
b11 %
b11 )
b11 6
1&
#110000
0&
#115000
b0 4
1&
#120000
0&
#125000
1"
b101 5
b11 4
b100 %
b100 )
b100 6
1&
#130000
0&
#135000
1"
b10 4
1&
#140000
0&
#145000
1"
b1 4
1&
#150000
0&
#155000
1"
b0 4
1&
#160000
0&
#165000
0"
b110 5
b1 4
b101 %
b101 )
b101 6
1&
#170000
0&
#175000
b0 4
1&
#180000
0&
#185000
1!
b111 5
b11 4
b110 %
b110 )
b110 6
1&
#190000
0&
#195000
1!
b10 4
1&
#200000
0&
#205000
1!
b1 4
1&
#210000
0&
#215000
1!
b0 4
1&
#220000
0&
#225000
0!
b0 5
b1 4
b111 %
b111 )
b111 6
1&
#230000
0&
#235000
b0 4
1&
#240000
0&
#245000
1#
b1 5
b11 4
b0 %
b0 )
b0 6
1&
#250000
0&
#255000
1#
b10 4
1&
#260000
0&
#265000
1#
b1 4
1&
#270000
0&
#275000
1#
b0 4
1&
#280000
0&
#285000
0#
b10 5
b1 4
b1 %
b1 )
b1 6
1&
#290000
0&
#295000
b0 4
1&
#300000
0&
#305000
1$
b11 5
b11 4
b10 %
b10 )
b10 6
1&
#310000
1!
1"
1#
1$
0&
1'
#315000
b1 5
0!
0"
0$
0#
b0 %
b0 )
b0 6
b10 4
1&
#320000
0&
#325000
1!
1"
1$
1#
b1 4
1&
#330000
0&
#335000
0!
0"
0$
0#
b0 4
1&
#340000
0&
#345000
1!
1"
1$
1#
b1 4
1&
#350000
0&
#355000
0!
0"
0$
0#
b0 4
1&
#360000
0&
#365000
1!
1"
1$
1#
b1 4
1&
#370000
0&
#375000
0!
0"
0$
0#
b0 4
1&
#380000
0&
#385000
1!
1"
1$
1#
b1 4
1&
#390000
0&
#395000
0!
0"
0$
0#
b0 4
1&
#400000
0&
#405000
1!
1"
1$
1#
b1 4
1&
#410000
0&
#415000
0!
0"
0$
0#
b0 4
1&
#420000
0&
#425000
1!
1"
1$
1#
b1 4
1&
#430000
0&
#435000
0!
0"
0$
0#
b0 4
1&
#440000
0&
#445000
1!
1"
1$
1#
b1 4
1&
#450000
0&
#455000
0!
0"
0$
0#
b0 4
1&
#460000
1#
0&
0'
#465000
0#
b10 5
b1 4
b1 %
b1 )
b1 6
1&
#470000
0&
#475000
b0 4
1&
#480000
0&
#485000
1$
b11 5
b11 4
b10 %
b10 )
b10 6
1&
#490000
0&
#495000
1$
b10 4
1&
#500000
0&
#505000
1$
b1 4
1&
#510000
0&
#515000
1$
b0 4
1&
#520000
0&
#525000
0$
b100 5
b1 4
b11 %
b11 )
b11 6
1&
#530000
0&
#535000
b0 4
1&
#540000
0&
#545000
1"
b101 5
b11 4
b100 %
b100 )
b100 6
1&
#550000
0&
#555000
1"
b10 4
1&
#560000
0&
#565000
1"
b1 4
1&
#570000
0&
#575000
1"
b0 4
1&
#580000
0&
#585000
0"
b110 5
b1 4
b101 %
b101 )
b101 6
1&
#590000
0&
#595000
b0 4
1&
#600000
0&
#605000
1!
b111 5
b11 4
b110 %
b110 )
b110 6
1&
#610000
0&
#615000
1!
b10 4
1&
#620000
0&
#625000
1!
b1 4
1&
#630000
0&
#635000
1!
b0 4
1&
#640000
0&
#645000
0!
b0 5
b1 4
b111 %
b111 )
b111 6
1&
#650000
0&
#655000
b0 4
1&
#660000
0&
#665000
1#
b1 5
b11 4
b0 %
b0 )
b0 6
1&
#670000
0&
#675000
1#
b10 4
1&
#680000
0&
#685000
1#
b1 4
1&
#690000
0&
#695000
1#
b0 4
1&
#700000
0&
#705000
0#
b10 5
b1 4
b1 %
b1 )
b1 6
1&
#710000
0&
#715000
b0 4
1&
#720000
0&
#725000
1$
b11 5
b11 4
b10 %
b10 )
b10 6
1&
#730000
0&
#735000
1$
b10 4
1&
#740000
0&
#745000
1$
b1 4
1&
#750000
0&
#755000
1$
b0 4
1&
